smartenforcement/__init__.py
smartenforcement-0.0.1.dist-info/licenses/LICENSE
smartenforcement-0.0.1.dist-info/METADATA
smartenforcement-0.0.1.dist-info/WHEEL
smartenforcement-0.0.1.dist-info/top_level.txt
smartenforcement-0.0.1.dist-info/RECORD
