Metadata-Version: 2.4
Name: smartenforcement
Version: 0.0.1
Summary: A placeholder for a project in planning. This package reserves the namespace for future development.
Author: 
Author-email: 
Classifier: Development Status :: 1 - Planning
Classifier: Intended Audience :: Developers
Classifier: Programming Language :: Python :: 3
Classifier: Programming Language :: Python :: 3.7
Classifier: Programming Language :: Python :: 3.8
Classifier: Programming Language :: Python :: 3.9
Classifier: Programming Language :: Python :: 3.10
Classifier: Programming Language :: Python :: 3.11
Requires-Python: >=3.7
License-File: LICENSE
Dynamic: license-file
Dynamic: requires-python
